muid/__init__.py
muid/animals.json
muid/corpus.py
muid/crypto.py
muid/explanation.py
muid/mining.py
muid/stupid_dog_tricks.py
muid/validation.py
muid-0.5.3.dist-info/METADATA
muid-0.5.3.dist-info/WHEEL
muid-0.5.3.dist-info/entry_points.txt
muid-0.5.3.dist-info/top_level.txt
muid-0.5.3.dist-info/RECORD
