Metadata-Version: 2.1
Name: muid
Version: 0.5.3
Summary: Memorable Unique Identifier
Home-page: https://github.com/microprediction/muid
Author: microprediction
Author-email: info@microprediction.com
License: MIT
Platform: UNKNOWN
Classifier: License :: OSI Approved :: MIT License
Classifier: Programming Language :: Python :: 3
Classifier: Programming Language :: Python :: 3.7
Requires-Dist: contexttimer
